examplePackageYassun/__init__.py
examplePackageYassun/example.py
examplePackageYassun-2.1.1.dist-info/LICENSE
examplePackageYassun-2.1.1.dist-info/METADATA
examplePackageYassun-2.1.1.dist-info/WHEEL
examplePackageYassun-2.1.1.dist-info/top_level.txt
examplePackageYassun-2.1.1.dist-info/RECORD
