Metadata-Version: 2.1
Name: examplePackageYassun
Version: 2.1.1
Summary: A small example package
Author-email: Yassun BlueLightning <yassunapp@gmail.com>
License: Copyright (c) 2022 Yasushi Yassun Obata        
Project-URL: Homepage, https://www.facebook.com/yassunapp
Project-URL: Bug Tracker, https://www.facebook.com/yassunapp
Classifier: Programming Language :: Python :: 3
Classifier: License :: OSI Approved :: MIT License
Classifier: Operating System :: OS Independent
Requires-Python: >=3.7
License-File: LICENSE
